pyecoacc/__init__.py
pyecoacc/features/__init__.py
pyecoacc/features/stats.py
pyecoacc/features/transform.py
pyecoacc/models/__init__.py
pyecoacc/models/pipeline.py
pyecoacc/models/deep/__init__.py
pyecoacc/models/deep/cnn.py
pyecoacc/util/__init__.py
pyecoacc/util/analytics.py
pyecoacc/util/time_budget.py
pyecoacc/util/training.py
pyecoacc-1.0.0.dist-info/licenses/LICENSE
pyecoacc-1.0.0.dist-info/METADATA
pyecoacc-1.0.0.dist-info/WHEEL
pyecoacc-1.0.0.dist-info/top_level.txt
pyecoacc-1.0.0.dist-info/RECORD
