Metadata-Version: 2.4
Name: pyecoacc
Version: 1.0.0
Summary: A python package for supervised learning of behavioral modes from sensor data.
Author-email: Hezi Resheff <Hezi.Resheff+pyecoacc@gmail.com>
License:                     GNU GENERAL PUBLIC LICENSE
Project-URL: Homepage, https://github.com/Hezi-Resheff/pyecoacc
Project-URL: Repository, https://github.com/Hezi-Resheff/pyecoacc
Requires-Python: >=3.8
License-File: LICENSE
Requires-Dist: numpy
Requires-Dist: pandas
Requires-Dist: scikit-learn
Requires-Dist: torch
Requires-Dist: skorch
Dynamic: license-file
